SoundForCp/SoundForCp.py
SoundForCp/__init__.py
SoundForCp-0.0.2.dist-info/LICENSE
SoundForCp-0.0.2.dist-info/METADATA
SoundForCp-0.0.2.dist-info/WHEEL
SoundForCp-0.0.2.dist-info/entry_points.txt
SoundForCp-0.0.2.dist-info/top_level.txt
SoundForCp-0.0.2.dist-info/RECORD
