Metadata-Version: 2.1
Name: SoundForCp
Version: 0.0.2
Summary: A software package for calculating specific heat capacity based on sound velocity method.
Home-page: https://github.com/JunPei-China/SoundForCp
Author: JunPei-China
Author-email: Jun_Pei@163.com
License: UNKNOWN
Project-URL: Bug Tracker, https://github.com/JunPei-China/SoundForCp/issues
Platform: UNKNOWN
Classifier: Programming Language :: Python :: 3
Classifier: License :: OSI Approved :: GNU General Public License v3 (GPLv3)
Classifier: Operating System :: OS Independent
Requires-Python: >=3.6
License-File: LICENSE
Requires-Dist: numpy (>=1.20)
Requires-Dist: scipy (>=1.7)
Requires-Dist: PyYaml (>=6.0)
